phicode-2.6.0.dist-info/licenses/LICENSE
phicode_engine/__init__.py
phicode_engine/__main__.py
phicode_engine/engine.py
phicode_engine/api/__init__.py
phicode_engine/api/cli.py
phicode_engine/api/http_server.py
phicode_engine/api/subprocess_handler.py
phicode_engine/benchsuite/__init__.py
phicode_engine/benchsuite/bench_cache.φ
phicode_engine/benchsuite/bench_extreme_stress.φ
phicode_engine/benchsuite/bench_memory.φ
phicode_engine/benchsuite/bench_stress.φ
phicode_engine/benchsuite/bench_symbol_density.φ
phicode_engine/benchsuite/bench_transpiler.φ
phicode_engine/benchsuite/bench_transpiler_patterns.φ
phicode_engine/benchsuite/bench_transpiler_scaling.φ
phicode_engine/benchsuite/benchmark_cli.py
phicode_engine/benchsuite/benchmark_commands.py
phicode_engine/benchsuite/benchmark_core.py
phicode_engine/benchsuite/benchmark_prints.py
phicode_engine/benchsuite/benchmark_visualizer.py
phicode_engine/benchsuite/system_info.py
phicode_engine/benchsuite/simulation/simulate_concurrency.φ
phicode_engine/benchsuite/simulation/simulate_crash.φ
phicode_engine/benchsuite/simulation/simulate_import_burst.φ
phicode_engine/benchsuite/simulation/simulate_phimmuno_threat.φ
phicode_engine/benchsuite/simulation/simulate_stress_transpiler.φ
phicode_engine/benchsuite/simulation/simulate_workload_cache.φ
phicode_engine/config/config.py
phicode_engine/config/version.py
phicode_engine/core/phicode_logger.py
phicode_engine/core/cache/phicode_bytecode.py
phicode_engine/core/cache/phicode_cache.py
phicode_engine/core/cache/phicode_cache_ops.py
phicode_engine/core/cache/phicode_cache_validation.py
phicode_engine/core/importing/phicode_central.py
phicode_engine/core/importing/phicode_finder.py
phicode_engine/core/importing/phicode_importer.py
phicode_engine/core/interpreter/phicode_args.py
phicode_engine/core/interpreter/phicode_executor.py
phicode_engine/core/interpreter/phicode_exit_handlers.py
phicode_engine/core/interpreter/phicode_interpreter.py
phicode_engine/core/interpreter/phicode_interpreter_display.py
phicode-2.6.0.dist-info/METADATA
phicode-2.6.0.dist-info/WHEEL
phicode-2.6.0.dist-info/entry_points.txt
phicode-2.6.0.dist-info/top_level.txt
phicode-2.6.0.dist-info/RECORD
