Metadata-Version: 2.4
Name: phicode
Version: 2.6.0
Summary: (φ) Phicode Runtime Engine — Optimized for stability under load (CPython/PyPy Supported)
Author-email: Jay Baleine <jay@banes-lab.com>
License: Phicode License
Requires-Python: >=3.8
License-File: LICENSE
Requires-Dist: xxhash>=3.0.0
Requires-Dist: regex>=2025.7.34
Provides-Extra: utility
Requires-Dist: psutil>=5.8.0; extra == "utility"
Provides-Extra: rust
Dynamic: license-file
